{
    "id": "ultima-torcia",
    "title": "L'Ultima Torcia",
    "version": "1.0.0",
    "compatibility": {
        "minimum": "12",
        "verified": "13"
    },
    "authors": [
        {
            "name": "guido92",
            "flags": {}
        }
    ],
    "esmodules": [
        "module/ultima-torcia.mjs"
    ],
    "styles": [
        "css/ultima-torcia.css"
    ],
    "documentTypes": {
        "Actor": {
            "character": {},
            "monster": {},
            "npc": {}
        },
        "Item": {
            "weapon": {},
            "armor": {},
            "consumable": {},
            "skill": {},
            "spell": {},
            "feature": {}
        }
    },
    "packFolders": [],
    "packs": [],
    "languages": [
        {
            {
                "id": "ultima-torcia",
                "title": "L'Ultima Torcia",
                "version": "1.0.0",
                "compatibility": {
                    "minimum": "12",
                    "verified": "13"
                },
                "authors": [
                    {
                        "name": "guido92",
                        "flags": {}
                    }
                ],
                "esmodules": [
                    "module/ultima-torcia.mjs"
                ],
                "styles": [
                    "css/ultima-torcia.css"
                ],
                "documentTypes": {
                    "Actor": {
                        "character": {},
                        "monster": {},
                        "npc": {}
                    },
                    "Item": {
                        "weapon": {},
                        "armor": {},
                        "consumable": {},
                        "skill": {},
                        "spell": {},
                        "feature": {}
                    }
                },
                "packFolders": [],
                "packs": [],
                "languages": [
                    {
                        "lang": "it",
                        "name": "Italiano",
                        "path": "lang/it.json"
                    }
                ],
                "socket": false,
                "url": "https://github.com/guido92/Ultima-Torcia---Foundry-VTT",
                "manifest": "https://raw.githubusercontent.com/guido92/Ultima-Torcia---Foundry-VTT/main/system.json",
                "download": "https://github.com/guido92/Ultima-Torcia---Foundry-VTT/raw/main/system.zip",
                "license": "LICENSE"
            }